servicenow_provider/__init__.py
servicenow_provider/example_dags/sample.py
servicenow_provider/hooks/__init__.py
servicenow_provider/hooks/servicenow.py
servicenow_provider/operators/__init__.py
servicenow_provider/operators/servicenow.py
servicenow_provider/operators/servicenowinsert.py
servicenow_provider/operators/servicenowsearch.py
servicenow_provider/operators/servicenowupdate.py
servicenow_provider/sensors/__init__.py
servicenow_provider/sensors/sample.py
airflow_provider_servicenow-1.0.1.dist-info/LICENSE
airflow_provider_servicenow-1.0.1.dist-info/METADATA
airflow_provider_servicenow-1.0.1.dist-info/WHEEL
airflow_provider_servicenow-1.0.1.dist-info/entry_points.txt
airflow_provider_servicenow-1.0.1.dist-info/top_level.txt
airflow_provider_servicenow-1.0.1.dist-info/RECORD
