Metadata-Version: 2.1
Name: airflow-provider-servicenow
Version: 1.0.1
Summary: A Service Now Apache Airflow provider package built by Hongmin.
Author-email: hongmin zhang <hongmin.zhang.-nd@disney.com>
License: Apache License 2.0
Project-URL: Homepage, https://xxx.org
Project-URL: Source, https://xxx.org/xxx/xxx
Classifier: Framework :: Apache Airflow
Classifier: Framework :: Apache Airflow :: Provider
Requires-Python: ~=3.11
License-File: LICENSE
Requires-Dist: apache-airflow (>=2.6)
Requires-Dist: pysnc (>=1.1.4)
